seriesbutler/__init__.py
seriesbutler/cli.py
seriesbutler/datasources.py
seriesbutler/functions.py
seriesbutler/models.py
seriesbutler/providers.py
seriesbutler-1.2.1.dist-info/DESCRIPTION.rst
seriesbutler-1.2.1.dist-info/METADATA
seriesbutler-1.2.1.dist-info/RECORD
seriesbutler-1.2.1.dist-info/WHEEL
seriesbutler-1.2.1.dist-info/entry_points.txt
seriesbutler-1.2.1.dist-info/metadata.json
seriesbutler-1.2.1.dist-info/top_level.txt
