Metadata-Version: 2.0
Name: seriesbutler
Version: 1.2.1
Summary: Grab your favourite TV shows
Home-page: https://github.com/raphiz/seriesbutler
Author: Raphael Zimmermann
Author-email: dev@raphael.li
License: MIT
Platform: Linux
Platform: BSD
Platform: MacOS
Classifier: Programming Language :: Python
Classifier: Programming Language :: Python :: 3.4
Classifier: Programming Language :: Python :: Implementation :: CPython
Classifier: Development Status :: 4 - Beta
Requires-Dist: beautifulsoup4 (>=4.4)
Requires-Dist: click (==5.1)
Requires-Dist: configobj (==5.0.6)
Requires-Dist: jsonschema (==2.5.1)
Requires-Dist: requests (>=2.8)
Requires-Dist: youtube-dl
